libsbml/__init__.py
libsbml/_libsbml.cp312-win_arm64.pyd
python_libsbml-5.21.0.dist-info/licenses/LICENSE.html
python_libsbml-5.21.0.dist-info/licenses/LICENSE.txt
python_libsbml-5.21.0.dist-info/METADATA
python_libsbml-5.21.0.dist-info/WHEEL
python_libsbml-5.21.0.dist-info/top_level.txt
python_libsbml-5.21.0.dist-info/RECORD
