Metadata-Version: 2.4
Name: python-libsbml
Version: 5.21.0
Summary: LibSBML Python API
Home-page: http://sbml.org
Author: SBML Team
Author-email: libsbml-team@googlegroups.com
License: LGPL
License-File: LICENSE.html
License-File: LICENSE.txt
Dynamic: author
Dynamic: author-email
Dynamic: description
Dynamic: home-page
Dynamic: license
Dynamic: license-file
Dynamic: summary
